company_mcp/__init__.py
company_mcp/api_clients.py
company_mcp/cache.py
company_mcp/models.py
company_mcp/server.py
navam/.mcp.json
navam/README.md
navam/__init__.py
navam/__main__.py
navam/cache_manager.py
navam/chat.py
navam/cli.py
navam/simple_chat.py
navam/sync.py
navam/tools.py
navam/.claude/agents/atlas-investment-strategist.md
navam/.claude/agents/cash-treasury-steward.md
navam/.claude/agents/compass-goal-planner.md
navam/.claude/agents/compliance-sentinel.md
navam/.claude/agents/earnings-whisperer.md
navam/.claude/agents/factor-scout.md
navam/.claude/agents/hedge-smith-options.md
navam/.claude/agents/ledger-performance-analyst.md
navam/.claude/agents/macro-lens-strategist.md
navam/.claude/agents/news-sentry-market-watch.md
navam/.claude/agents/notionist-librarian.md
navam/.claude/agents/quant-portfolio-optimizer.md
navam/.claude/agents/quill-equity-analyst.md
navam/.claude/agents/rebalance-bot.md
navam/.claude/agents/risk-shield-manager.md
navam/.claude/agents/screen-forge.md
navam/.claude/agents/tax-scout.md
navam/.claude/agents/trader-jane-execution.md
navam/.claude/commands/invest/README.md
navam/.claude/commands/invest/execute-rebalance.md
navam/.claude/commands/invest/monitor-holdings.md
navam/.claude/commands/invest/optimize-taxes.md
navam/.claude/commands/invest/plan-goals.md
navam/.claude/commands/invest/research-stock.md
navam/.claude/commands/invest/review-portfolio.md
navam/.claude/commands/invest/screen-opportunities.md
navam/agents/atlas-investment-strategist.md
navam/agents/cash-treasury-steward.md
navam/agents/compass-goal-planner.md
navam/agents/compliance-sentinel.md
navam/agents/earnings-whisperer.md
navam/agents/factor-scout.md
navam/agents/hedge-smith-options.md
navam/agents/ledger-performance-analyst.md
navam/agents/macro-lens-strategist.md
navam/agents/news-sentry-market-watch.md
navam/agents/notionist-librarian.md
navam/agents/quant-portfolio-optimizer.md
navam/agents/quill-equity-analyst.md
navam/agents/rebalance-bot.md
navam-1.5.11.dist-info/licenses/LICENSE
navam-1.5.11.dist-info/METADATA
navam-1.5.11.dist-info/WHEEL
navam-1.5.11.dist-info/entry_points.txt
navam-1.5.11.dist-info/top_level.txt
navam-1.5.11.dist-info/RECORD
