Metadata-Version: 2.4
Name: navam
Version: 1.5.11
Summary: Personal AI agents for investing, shopping, health, and learning
Author-email: "Navam.io" <team@navam.io>
Maintainer-email: "Navam.io" <team@navam.io>
License: MIT
Keywords: ai,agents,personal,investing,shopping,health,learning,claude,mcp,assistant,finance,portfolio,wellness,education
Classifier: Development Status :: 4 - Beta
Classifier: Intended Audience :: End Users/Desktop
Classifier: Intended Audience :: Developers
Classifier: Topic :: Scientific/Engineering :: Artificial Intelligence
Classifier: Topic :: Education
Classifier: Topic :: Office/Business :: Scheduling
Classifier: License :: OSI Approved :: MIT License
Classifier: Programming Language :: Python :: 3
Classifier: Programming Language :: Python :: 3.11
Classifier: Programming Language :: Python :: 3.12
Classifier: Operating System :: OS Independent
Requires-Python: >=3.11
License-File: LICENSE
Requires-Dist: mcp[cli]>=0.9.0
Requires-Dist: yfinance>=0.2.0
Requires-Dist: python-dotenv>=1.0.0
Requires-Dist: pydantic>=2.0.0
Requires-Dist: aiohttp>=3.9.0
Requires-Dist: pandas>=2.0.0
Requires-Dist: numpy>=1.24.0
Requires-Dist: pyyaml>=6.0.0
Requires-Dist: claude-agent-sdk>=0.1.0
Requires-Dist: anyio>=3.7.0
Requires-Dist: rich>=13.0.0
Requires-Dist: prompt-toolkit>=3.0.0
Requires-Dist: click>=8.0.0
Requires-Dist: finnhub-python>=2.4.0
Requires-Dist: newsapi-python>=0.2.0
Requires-Dist: alpha-vantage>=2.3.0
Requires-Dist: build>=1.3.0
Requires-Dist: fastmcp>=0.1.0
Provides-Extra: dev
Requires-Dist: pytest>=7.0.0; extra == "dev"
Requires-Dist: pytest-asyncio>=0.21.0; extra == "dev"
Requires-Dist: pytest-cov>=4.0.0; extra == "dev"
Requires-Dist: black>=23.0.0; extra == "dev"
Requires-Dist: mypy>=1.0.0; extra == "dev"
Requires-Dist: ruff>=0.1.0; extra == "dev"
Requires-Dist: pre-commit>=3.0.0; extra == "dev"
Requires-Dist: sphinx>=6.0.0; extra == "dev"
Requires-Dist: sphinx-rtd-theme>=1.2.0; extra == "dev"
Provides-Extra: all
Requires-Dist: navam[dev]; extra == "all"
Dynamic: license-file
